{
	"schemaVersion": 2,
	"mediaType": "application/vnd.oci.image.manifest.v1+json",
	"config": {
		"mediaType": "application/vnd.oci.image.config.v1+json",
		"digest": "sha256:660b790bb0807cd11ce770e22219a830fec2d34a82ec52e9dda2aa39a0cbe6a7",
		"size": 393
	},
	"layers": [
		{
			"mediaType": "application/vnd.oci.image.layer.v1.tar+gzip",
			"digest": "sha256:94e95b322094a857524f076d8e3edec7eb321ea1c04b6d4e3ccd36c4a3b44c8d",
			"size": 892155
		}
	],
	"annotations": {
		"org.opencontainers.image.url": "https://github.com/docker-library/busybox",
		"org.opencontainers.image.version": "1.37.0-musl"
	}
}
