{
	"schemaVersion": 2,
	"mediaType": "application/vnd.oci.image.index.v1+json",
	"manifests": [
		{
			"mediaType": "application/vnd.oci.image.manifest.v1+json",
			"digest": "sha256:7a3a1df7e0d5907290431b6fc9df683513abb571a9c702179a62f4b35518d279",
			"size": 608,
			"platform": {
				"architecture": "arm64",
				"os": "linux",
				"variant": "v8"
			},
			"annotations": {
				"org.opencontainers.image.ref.name": "busybox:1.37.0-musl",
				"io.containerd.image.name": "busybox:1.37.0-musl"
			}
		}
	]
}
