{
	"schemaVersion": 2,
	"mediaType": "application/vnd.oci.image.manifest.v1+json",
	"config": {
		"mediaType": "application/vnd.oci.image.config.v1+json",
		"digest": "sha256:0c2a926261a9cc7e6b4b42aaf4c883738baaaa516f2dedb8a30a6895474547ff",
		"size": 464
	},
	"layers": [
		{
			"mediaType": "application/vnd.oci.image.layer.v1.tar+gzip",
			"digest": "sha256:e56ee2ce0a95cb5d17c19bac80501a4e6595b736e0d366577ba4fc49211ddf6e",
			"size": 944295
		}
	],
	"annotations": {
		"org.opencontainers.image.url": "https://github.com/docker-library/busybox",
		"org.opencontainers.image.version": "1.37.0-musl"
	}
}
