{
	"schemaVersion": 2,
	"mediaType": "application/vnd.oci.image.index.v1+json",
	"manifests": [
		{
			"mediaType": "application/vnd.oci.image.manifest.v1+json",
			"digest": "sha256:8184cf6cfc9b685fce172c8c587c71194f4da5a34111e3165ddfb3d6ebe73fca",
			"size": 610,
			"platform": {
				"architecture": "arm",
				"os": "linux",
				"variant": "v5"
			},
			"annotations": {
				"org.opencontainers.image.ref.name": "busybox:1.37.0-uclibc",
				"io.containerd.image.name": "busybox:1.37.0-uclibc"
			}
		}
	]
}
