{
	"schemaVersion": 2,
	"mediaType": "application/vnd.oci.image.manifest.v1+json",
	"config": {
		"mediaType": "application/vnd.oci.image.config.v1+json",
		"digest": "sha256:cab2d6d0df938a13eab9a8ba186c16d4b323c3f3001abd273f802f10bf97b66d",
		"size": 388
	},
	"layers": [
		{
			"mediaType": "application/vnd.oci.image.layer.v1.tar+gzip",
			"digest": "sha256:ef5356a78014f89f744e404ef156f976bf23f8978c9a523e018b1fd82a04f0b7",
			"size": 1557914
		}
	],
	"annotations": {
		"org.opencontainers.image.url": "https://github.com/docker-library/busybox",
		"org.opencontainers.image.version": "1.37.0-glibc"
	}
}
