{
	"schemaVersion": 2,
	"mediaType": "application/vnd.oci.image.manifest.v1+json",
	"config": {
		"mediaType": "application/vnd.oci.image.config.v1+json",
		"digest": "sha256:2539776ce5113e7e10dc9b4349634418c895d693fa26f179f74fe276b954a90a",
		"size": 480
	},
	"layers": [
		{
			"mediaType": "application/vnd.oci.image.layer.v1.tar+gzip",
			"digest": "sha256:a12bd3844df3c1bd994e3d6d970baae5e71618228966f1f9c2a277f967cee5db",
			"size": 895778
		}
	],
	"annotations": {
		"org.opencontainers.image.url": "https://github.com/docker-library/busybox",
		"org.opencontainers.image.version": "1.36.1-musl"
	}
}
