{
	"schemaVersion": 2,
	"mediaType": "application/vnd.oci.image.manifest.v1+json",
	"config": {
		"mediaType": "application/vnd.oci.image.config.v1+json",
		"digest": "sha256:9ab8d031e7b08e5cebd44f8651737251e97927707a063698a5caf2f795d3063b",
		"size": 374
	},
	"layers": [
		{
			"mediaType": "application/vnd.oci.image.layer.v1.tar+gzip",
			"digest": "sha256:3973f53d918951736fa91951b10f5a21efc8abd2c12b61bbebc34f2f8d24e196",
			"size": 2461508
		}
	],
	"annotations": {
		"org.opencontainers.image.url": "https://github.com/docker-library/busybox",
		"org.opencontainers.image.version": "1.36.1-glibc"
	}
}
