{
	"schemaVersion": 2,
	"mediaType": "application/vnd.oci.image.manifest.v1+json",
	"config": {
		"mediaType": "application/vnd.oci.image.config.v1+json",
		"digest": "sha256:712434995df33c978832e28097f000b73420798d05bc3a357e1856403072cdf2",
		"size": 481
	},
	"layers": [
		{
			"mediaType": "application/vnd.oci.image.layer.v1.tar+gzip",
			"digest": "sha256:758b6efafaf193f0b7a36538bd1107c7829b2540c3ac40305825f60f9c320d59",
			"size": 904242
		}
	],
	"annotations": {
		"org.opencontainers.image.url": "https://github.com/docker-library/busybox",
		"org.opencontainers.image.version": "1.36.1-uclibc"
	}
}
