{
	"schemaVersion": 2,
	"mediaType": "application/vnd.oci.image.index.v1+json",
	"manifests": [
		{
			"mediaType": "application/vnd.oci.image.manifest.v1+json",
			"digest": "sha256:7b1dee78b9779b84dbe25afbec313f6e8074f34b89b50545872eeaff2c14d8f4",
			"size": 610,
			"platform": {
				"architecture": "arm",
				"os": "linux",
				"variant": "v7"
			},
			"annotations": {
				"org.opencontainers.image.ref.name": "busybox:1.36.1-uclibc",
				"io.containerd.image.name": "busybox:1.36.1-uclibc"
			}
		}
	]
}
